{ 
  "anchor":1,
  "geojson": {
    "type": "FeatureCollection",
    "features": [
      { "type": "Feature", "geometry": { "type": "Point", "coordinates": [1.148113, 49.027769]}, "properties": { "name": "La Vieille Gabelle",           "radius": 100, "code": "0001" }},
      { "type": "Feature", "geometry": { "type": "Point", "coordinates": [1.152286, 49.027544]}, "properties": { "name": "Côté Rotisserie",              "radius": 100, "code": "0002" }},
      { "type": "Feature", "geometry": { "type": "Point", "coordinates": [1.146750, 49.027192]}, "properties": { "name": "Le 17",                        "radius": 50, "code": "0004" }}
    ]
  }
}
